django_query_builder_widget/__init__.py
django_query_builder_widget/tests.py
django_query_builder_widget/utils.py
django_query_builder_widget/widgets.py
django_query_builder_widget/static/query-builder-widget/css/query-builder-widget.css
django_query_builder_widget/static/query-builder-widget/css/lib/query-builder.default.min.css
django_query_builder_widget/static/query-builder-widget/js/lib/jquery-3.6.0.min.js
django_query_builder_widget/static/query-builder-widget/js/lib/query-builder.standalone.min.js
django_query_builder_widget-0.0.7.dist-info/licenses/LICENSE
django_query_builder_widget-0.0.7.dist-info/METADATA
django_query_builder_widget-0.0.7.dist-info/WHEEL
django_query_builder_widget-0.0.7.dist-info/top_level.txt
django_query_builder_widget-0.0.7.dist-info/RECORD
