Metadata-Version: 2.4
Name: django-query-builder-widget
Version: 0.0.7
Summary: A Django admin widget for building complex queries using jQuery QueryBuilder
Home-page: https://github.com/Matheus-BM/django-query-builder-widget
Author: MatheusBM
Author-email: MatheusBM <contato@matheusbm.com>
License: MIT
Project-URL: Homepage, https://github.com/Matheus-BM/django-query-builder-widget
Project-URL: Repository, https://github.com/Matheus-BM/django-query-builder-widget
Project-URL: Issues, https://github.com/Matheus-BM/django-query-builder-widget/issues
Keywords: django,widget,query-builder,admin,filter
Classifier: Development Status :: 3 - Alpha
Classifier: Framework :: Django
Classifier: Framework :: Django :: 3.2
Classifier: Framework :: Django :: 4.0
Classifier: Framework :: Django :: 4.1
Classifier: Framework :: Django :: 4.2
Classifier: Framework :: Django :: 5.0
Classifier: Intended Audience :: Developers
Classifier: License :: OSI Approved :: MIT License
Classifier: Operating System :: OS Independent
Classifier: Programming Language :: Python
Classifier: Programming Language :: Python :: 3
Classifier: Programming Language :: Python :: 3.8
Classifier: Programming Language :: Python :: 3.9
Classifier: Programming Language :: Python :: 3.10
Classifier: Programming Language :: Python :: 3.11
Classifier: Programming Language :: Python :: 3.12
Classifier: Topic :: Software Development :: Libraries :: Python Modules
Requires-Python: >=3.8
License-File: LICENSE
Requires-Dist: Django>=3.2
Provides-Extra: dev
Requires-Dist: pytest>=7.0; extra == "dev"
Requires-Dist: pytest-django>=4.5; extra == "dev"
Requires-Dist: black>=23.0; extra == "dev"
Requires-Dist: flake8>=6.0; extra == "dev"
Dynamic: author
Dynamic: home-page
Dynamic: license-file
Dynamic: requires-python
